selectors34.py
selectors34-1.2.dist-info/DESCRIPTION.rst
selectors34-1.2.dist-info/METADATA
selectors34-1.2.dist-info/RECORD
selectors34-1.2.dist-info/WHEEL
selectors34-1.2.dist-info/metadata.json
selectors34-1.2.dist-info/top_level.txt
