Metadata-Version: 1.1
Name: selectors34
Version: 1.2
Summary: Backport of the selectors module from Python 3.4.
Home-page: https://github.com/berkerpeksag/selectors34
Author: Berker Peksag
Author-email: berker.peksag@gmail.com
License: Python Software Foundation License
Platform: UNKNOWN
Classifier: Programming Language :: Python :: 2
Classifier: Programming Language :: Python :: 2.6
Classifier: Programming Language :: Python :: 2.7
Classifier: Programming Language :: Python :: 3
Classifier: Programming Language :: Python :: 3.3
Classifier: License :: OSI Approved :: Python Software Foundation License
